deep_autograd/__init__.py
deep_autograd/engine.py
deep_autograd/nn.py
deep_autograd-0.0.2.dist-info/LICENSE
deep_autograd-0.0.2.dist-info/METADATA
deep_autograd-0.0.2.dist-info/WHEEL
deep_autograd-0.0.2.dist-info/RECORD
